async_pq/__init__.py
async_pq/queue.py
async_pq-0.3.1.dist-info/METADATA
async_pq-0.3.1.dist-info/RECORD
async_pq-0.3.1.dist-info/WHEEL
async_pq-0.3.1.dist-info/top_level.txt
