Metadata-Version: 2.1
Name: async-pq
Version: 0.3.1
Summary: Python async api for creating and managing queues in postgres
Home-page: https://github.com/maximdanilchenko/async-pq
Author: Danilchenko Maksim
Author-email: dmax.dev@gmail.com
License: MIT
Keywords: async postgresql asyncpg queue
Platform: UNKNOWN
Classifier: Development Status :: 3 - Alpha
Classifier: Intended Audience :: Developers
Classifier: License :: OSI Approved :: MIT License
Classifier: Natural Language :: English
Classifier: Programming Language :: Python :: 3.6
Requires-Dist: asyncpg
